ndef/__init__.py
ndef/bluetooth.py
ndef/deviceinfo.py
ndef/handover.py
ndef/message.py
ndef/record.py
ndef/signature.py
ndef/smartposter.py
ndef/text.py
ndef/uri.py
ndef/wifi.py
ndeflib-0.3.3.dist-info/LICENSE
ndeflib-0.3.3.dist-info/METADATA
ndeflib-0.3.3.dist-info/WHEEL
ndeflib-0.3.3.dist-info/top_level.txt
ndeflib-0.3.3.dist-info/RECORD
