Metadata-Version: 1.2
Name: ndeflib
Version: 0.3.3
Summary: NFC Data Exchange Format decoder and encoder.
Home-page: https://ndeflib.readthedocs.io/
Author: Stephen Tiedemann
Author-email: stephen.tiedemann@gmail.com
Maintainer: Stephen Tiedemann
Maintainer-email: stephen.tiedemann@gmail.com
License: ISC
Keywords: ndef,nfc
Platform: UNKNOWN
Classifier: Development Status :: 5 - Production/Stable
Classifier: Intended Audience :: Developers
Classifier: Natural Language :: English
Classifier: License :: OSI Approved :: ISC License (ISCL)
Classifier: Operating System :: OS Independent
Classifier: Programming Language :: Python
Classifier: Programming Language :: Python :: 2
Classifier: Programming Language :: Python :: 2.7
Classifier: Programming Language :: Python :: 3
Classifier: Programming Language :: Python :: 3.4
Classifier: Programming Language :: Python :: 3.5
Classifier: Programming Language :: Python :: Implementation :: CPython
Classifier: Programming Language :: Python :: Implementation :: PyPy
Classifier: Topic :: Software Development :: Libraries :: Python Modules
